huangjb_charset_normalizer/__init__.py
huangjb_charset_normalizer/_lib_build/charset_normalizer/__init__.pyc
huangjb_charset_normalizer/_lib_build/charset_normalizer/__main__.pyc
huangjb_charset_normalizer/_lib_build/charset_normalizer/api.pyc
huangjb_charset_normalizer/_lib_build/charset_normalizer/cd.pyc
huangjb_charset_normalizer/_lib_build/charset_normalizer/constant.pyc
huangjb_charset_normalizer/_lib_build/charset_normalizer/legacy.pyc
huangjb_charset_normalizer/_lib_build/charset_normalizer/md.cpython-313t-arm-linux-gnueabihf.so
huangjb_charset_normalizer/_lib_build/charset_normalizer/md.pyc
huangjb_charset_normalizer/_lib_build/charset_normalizer/md__mypyc.cpython-313t-arm-linux-gnueabihf.so
huangjb_charset_normalizer/_lib_build/charset_normalizer/models.pyc
huangjb_charset_normalizer/_lib_build/charset_normalizer/py.typed
huangjb_charset_normalizer/_lib_build/charset_normalizer/utils.pyc
huangjb_charset_normalizer/_lib_build/charset_normalizer/version.pyc
huangjb_charset_normalizer/_lib_build/charset_normalizer/cli/__init__.pyc
huangjb_charset_normalizer/_lib_build/charset_normalizer/cli/__main__.pyc
huangjb_charset_normalizer-3.4.2.dist-info/METADATA
huangjb_charset_normalizer-3.4.2.dist-info/WHEEL
huangjb_charset_normalizer-3.4.2.dist-info/top_level.txt
huangjb_charset_normalizer-3.4.2.dist-info/RECORD
